<annotation>
  <folder></folder>
  <filename>01772GL-022A-2D-130425.jpg</filename>
  <source>
    <database>Unknown</database>
    <annotation>Unknown</annotation>
    <image>Unknown</image>
  </source>
  <size>
    <width>2339</width>
    <height>1654</height>
    <depth></depth>
  </size>
  <segmented>0</segmented>
  <object>
    <name>dimension_text</name>
    <truncated>0</truncated>
    <occluded>0</occluded>
    <difficult>0</difficult>
    <bndbox>
      <xmin>1813.9</xmin>
      <ymin>494.78</ymin>
      <xmax>1888.54</xmax>
      <ymax>509.71</ymax>
    </bndbox>
    <attributes>
      <attribute>
        <name>rotation</name>
        <value>339.70000000000005</value>
      </attribute>
    </attributes>
  </object>
  <object>
    <name>dimension_text</name>
    <truncated>0</truncated>
    <occluded>0</occluded>
    <difficult>0</difficult>
    <bndbox>
      <xmin>1972.12</xmin>
      <ymin>491.34</ymin>
      <xmax>2042.58</xmax>
      <ymax>505.44</ymax>
    </bndbox>
    <attributes>
      <attribute>
        <name>rotation</name>
        <value>14.599999999999994</value>
      </attribute>
    </attributes>
  </object>
  <object>
    <name>dimension_text</name>
    <truncated>0</truncated>
    <occluded>0</occluded>
    <difficult>0</difficult>
    <bndbox>
      <xmin>2008.9</xmin>
      <ymin>1111.53</ymin>
      <xmax>2099.66</xmax>
      <ymax>1127.83</ymax>
    </bndbox>
    <attributes>
      <attribute>
        <name>rotation</name>
        <value>339.5</value>
      </attribute>
    </attributes>
  </object>
  <object>
    <name>dimension_text</name>
    <truncated>0</truncated>
    <occluded>0</occluded>
    <difficult>0</difficult>
    <bndbox>
      <xmin>875.86</xmin>
      <ymin>1453.51</ymin>
      <xmax>935.58</xmax>
      <ymax>1467.65</ymax>
    </bndbox>
    <attributes>
      <attribute>
        <name>rotation</name>
        <value>0.0</value>
      </attribute>
    </attributes>
  </object>
  <object>
    <name>anntotation_text</name>
    <truncated>0</truncated>
    <occluded>0</occluded>
    <difficult>0</difficult>
    <bndbox>
      <xmin>1382.47</xmin>
      <ymin>221.92</ymin>
      <xmax>1396.11</xmax>
      <ymax>240.48</ymax>
    </bndbox>
    <attributes>
      <attribute>
        <name>rotation</name>
        <value>0.0</value>
      </attribute>
    </attributes>
  </object>
  <object>
    <name>anntotation_text</name>
    <truncated>0</truncated>
    <occluded>0</occluded>
    <difficult>0</difficult>
    <bndbox>
      <xmin>1351.7</xmin>
      <ymin>222.52</ymin>
      <xmax>1364.25</xmax>
      <ymax>240.53</ymax>
    </bndbox>
    <attributes>
      <attribute>
        <name>rotation</name>
        <value>0.0</value>
      </attribute>
    </attributes>
  </object>
  <object>
    <name>dimension_text</name>
    <truncated>0</truncated>
    <occluded>0</occluded>
    <difficult>0</difficult>
    <bndbox>
      <xmin>1833.79</xmin>
      <ymin>424.3</ymin>
      <xmax>2037.29</xmax>
      <ymax>439.25</ymax>
    </bndbox>
    <attributes>
      <attribute>
        <name>rotation</name>
        <value>0.0</value>
      </attribute>
    </attributes>
  </object>
  <object>
    <name>title_block</name>
    <truncated>0</truncated>
    <occluded>0</occluded>
    <difficult>0</difficult>
    <bndbox>
      <xmin>127.19</xmin>
      <ymin>120.4</ymin>
      <xmax>182.86</xmax>
      <ymax>500.55999999999995</ymax>
    </bndbox>
    <attributes>
      <attribute>
        <name>rotation</name>
        <value>0.0</value>
      </attribute>
    </attributes>
  </object>
  <object>
    <name>title_block</name>
    <truncated>0</truncated>
    <occluded>0</occluded>
    <difficult>0</difficult>
    <bndbox>
      <xmin>1317.58</xmin>
      <ymin>1302.53</ymin>
      <xmax>2252.11</xmax>
      <ymax>1570.38</ymax>
    </bndbox>
    <attributes>
      <attribute>
        <name>rotation</name>
        <value>0.0</value>
      </attribute>
    </attributes>
  </object>
  <object>
    <name>object</name>
    <truncated>0</truncated>
    <occluded>0</occluded>
    <difficult>0</difficult>
    <bndbox>
      <xmin>226.3</xmin>
      <ymin>182.7</ymin>
      <xmax>460.05</xmax>
      <ymax>266.58</ymax>
    </bndbox>
    <attributes>
      <attribute>
        <name>rotation</name>
        <value>0.0</value>
      </attribute>
    </attributes>
  </object>
  <object>
    <name>object</name>
    <truncated>0</truncated>
    <occluded>0</occluded>
    <difficult>0</difficult>
    <bndbox>
      <xmin>211.14</xmin>
      <ymin>429.69</ymin>
      <xmax>371.42</xmax>
      <ymax>562.63</ymax>
    </bndbox>
    <attributes>
      <attribute>
        <name>rotation</name>
        <value>0.0</value>
      </attribute>
    </attributes>
  </object>
  <object>
    <name>object</name>
    <truncated>0</truncated>
    <occluded>0</occluded>
    <difficult>0</difficult>
    <bndbox>
      <xmin>246.51</xmin>
      <ymin>678.26</ymin>
      <xmax>407.58</xmax>
      <ymax>896.68</ymax>
    </bndbox>
    <attributes>
      <attribute>
        <name>rotation</name>
        <value>0.0</value>
      </attribute>
    </attributes>
  </object>
  <object>
    <name>object</name>
    <truncated>0</truncated>
    <occluded>0</occluded>
    <difficult>0</difficult>
    <bndbox>
      <xmin>453.62</xmin>
      <ymin>955.77</ymin>
      <xmax>686.19</xmax>
      <ymax>1026.48</ymax>
    </bndbox>
    <attributes>
      <attribute>
        <name>rotation</name>
        <value>0.0</value>
      </attribute>
    </attributes>
  </object>
  <object>
    <name>object</name>
    <truncated>0</truncated>
    <occluded>0</occluded>
    <difficult>0</difficult>
    <bndbox>
      <xmin>683.79</xmin>
      <ymin>208.2</ymin>
      <xmax>1152.38</xmax>
      <ymax>369.44</ymax>
    </bndbox>
    <attributes>
      <attribute>
        <name>rotation</name>
        <value>0.0</value>
      </attribute>
    </attributes>
  </object>
  <object>
    <name>object</name>
    <truncated>0</truncated>
    <occluded>0</occluded>
    <difficult>0</difficult>
    <bndbox>
      <xmin>1486.43</xmin>
      <ymin>466.35</ymin>
      <xmax>1496.65</xmax>
      <ymax>587.27</ymax>
    </bndbox>
    <attributes>
      <attribute>
        <name>rotation</name>
        <value>0.0</value>
      </attribute>
    </attributes>
  </object>
  <object>
    <name>object</name>
    <truncated>0</truncated>
    <occluded>0</occluded>
    <difficult>0</difficult>
    <bndbox>
      <xmin>685.17</xmin>
      <ymin>673.86</ymin>
      <xmax>1163.51</xmax>
      <ymax>1122.42</ymax>
    </bndbox>
    <attributes>
      <attribute>
        <name>rotation</name>
        <value>0.0</value>
      </attribute>
    </attributes>
  </object>
  <object>
    <name>object</name>
    <truncated>0</truncated>
    <occluded>0</occluded>
    <difficult>0</difficult>
    <bndbox>
      <xmin>715.48</xmin>
      <ymin>1286.66</ymin>
      <xmax>1182.8</xmax>
      <ymax>1436.96</ymax>
    </bndbox>
    <attributes>
      <attribute>
        <name>rotation</name>
        <value>0.0</value>
      </attribute>
    </attributes>
  </object>
  <object>
    <name>object</name>
    <truncated>0</truncated>
    <occluded>0</occluded>
    <difficult>0</difficult>
    <bndbox>
      <xmin>1380.34</xmin>
      <ymin>675.02</ymin>
      <xmax>1538.74</xmax>
      <ymax>895.65</ymax>
    </bndbox>
    <attributes>
      <attribute>
        <name>rotation</name>
        <value>0.0</value>
      </attribute>
    </attributes>
  </object>
  <object>
    <name>object</name>
    <truncated>0</truncated>
    <occluded>0</occluded>
    <difficult>0</difficult>
    <bndbox>
      <xmin>1713.19</xmin>
      <ymin>515.06</ymin>
      <xmax>2154.72</xmax>
      <ymax>958.21</ymax>
    </bndbox>
    <attributes>
      <attribute>
        <name>rotation</name>
        <value>0.0</value>
      </attribute>
    </attributes>
  </object>
  <object>
    <name>object</name>
    <truncated>0</truncated>
    <occluded>0</occluded>
    <difficult>0</difficult>
    <bndbox>
      <xmin>1313.51</xmin>
      <ymin>1058.57</ymin>
      <xmax>1782.11</xmax>
      <ymax>1234.98</ymax>
    </bndbox>
    <attributes>
      <attribute>
        <name>rotation</name>
        <value>0.0</value>
      </attribute>
    </attributes>
  </object>
  <object>
    <name>object</name>
    <truncated>0</truncated>
    <occluded>0</occluded>
    <difficult>0</difficult>
    <bndbox>
      <xmin>1961.8</xmin>
      <ymin>1069.79</ymin>
      <xmax>2043.84</xmax>
      <ymax>1216.9</ymax>
    </bndbox>
    <attributes>
      <attribute>
        <name>rotation</name>
        <value>0.0</value>
      </attribute>
    </attributes>
  </object>
  <object>
    <name>anntotation_text</name>
    <truncated>0</truncated>
    <occluded>0</occluded>
    <difficult>0</difficult>
    <bndbox>
      <xmin>1883.84</xmin>
      <ymin>1219.92</ymin>
      <xmax>2033.12</xmax>
      <ymax>1261.56</ymax>
    </bndbox>
    <attributes>
      <attribute>
        <name>rotation</name>
        <value>0.0</value>
      </attribute>
    </attributes>
  </object>
  <object>
    <name>anntotation_text</name>
    <truncated>0</truncated>
    <occluded>0</occluded>
    <difficult>0</difficult>
    <bndbox>
      <xmin>2133.85</xmin>
      <ymin>1249.7</ymin>
      <xmax>2254.85</xmax>
      <ymax>1302.34</ymax>
    </bndbox>
    <attributes>
      <attribute>
        <name>rotation</name>
        <value>0.0</value>
      </attribute>
    </attributes>
  </object>
  <object>
    <name>anntotation_text</name>
    <truncated>0</truncated>
    <occluded>0</occluded>
    <difficult>0</difficult>
    <bndbox>
      <xmin>2027.23</xmin>
      <ymin>966.22</ymin>
      <xmax>2130.16</xmax>
      <ymax>988.22</ymax>
    </bndbox>
    <attributes>
      <attribute>
        <name>rotation</name>
        <value>0.0</value>
      </attribute>
    </attributes>
  </object>
  <object>
    <name>anntotation_text</name>
    <truncated>0</truncated>
    <occluded>0</occluded>
    <difficult>0</difficult>
    <bndbox>
      <xmin>2167.09</xmin>
      <ymin>807.27</ymin>
      <xmax>2203.23</xmax>
      <ymax>845.85</ymax>
    </bndbox>
    <attributes>
      <attribute>
        <name>rotation</name>
        <value>0.0</value>
      </attribute>
    </attributes>
  </object>
  <object>
    <name>anntotation_text</name>
    <truncated>0</truncated>
    <occluded>0</occluded>
    <difficult>0</difficult>
    <bndbox>
      <xmin>1803.97</xmin>
      <ymin>404.57</ymin>
      <xmax>1839.89</xmax>
      <ymax>436.86</ymax>
    </bndbox>
    <attributes>
      <attribute>
        <name>rotation</name>
        <value>0.0</value>
      </attribute>
    </attributes>
  </object>
  <object>
    <name>anntotation_text</name>
    <truncated>0</truncated>
    <occluded>0</occluded>
    <difficult>0</difficult>
    <bndbox>
      <xmin>1565.7</xmin>
      <ymin>877.03</ymin>
      <xmax>1614.15</xmax>
      <ymax>910.42</ymax>
    </bndbox>
    <attributes>
      <attribute>
        <name>rotation</name>
        <value>0.0</value>
      </attribute>
    </attributes>
  </object>
  <object>
    <name>anntotation_text</name>
    <truncated>0</truncated>
    <occluded>0</occluded>
    <difficult>0</difficult>
    <bndbox>
      <xmin>1676.02</xmin>
      <ymin>909.5</ymin>
      <xmax>1707.22</xmax>
      <ymax>944.97</ymax>
    </bndbox>
    <attributes>
      <attribute>
        <name>rotation</name>
        <value>315.09999999999997</value>
      </attribute>
    </attributes>
  </object>
  <object>
    <name>anntotation_text</name>
    <truncated>0</truncated>
    <occluded>0</occluded>
    <difficult>0</difficult>
    <bndbox>
      <xmin>1307.92</xmin>
      <ymin>947.28</ymin>
      <xmax>1334.63</xmax>
      <ymax>971.64</ymax>
    </bndbox>
    <attributes>
      <attribute>
        <name>rotation</name>
        <value>0.0</value>
      </attribute>
    </attributes>
  </object>
  <object>
    <name>anntotation_text</name>
    <truncated>0</truncated>
    <occluded>0</occluded>
    <difficult>0</difficult>
    <bndbox>
      <xmin>1312.4</xmin>
      <ymin>990.73</ymin>
      <xmax>1376.04</xmax>
      <ymax>1008.02</ymax>
    </bndbox>
    <attributes>
      <attribute>
        <name>rotation</name>
        <value>0.0</value>
      </attribute>
    </attributes>
  </object>
  <object>
    <name>anntotation_text</name>
    <truncated>0</truncated>
    <occluded>0</occluded>
    <difficult>0</difficult>
    <bndbox>
      <xmin>1524.54</xmin>
      <ymin>990.73</ymin>
      <xmax>1622.75</xmax>
      <ymax>1012.73</ymax>
    </bndbox>
    <attributes>
      <attribute>
        <name>rotation</name>
        <value>0.0</value>
      </attribute>
    </attributes>
  </object>
  <object>
    <name>anntotation_text</name>
    <truncated>0</truncated>
    <occluded>0</occluded>
    <difficult>0</difficult>
    <bndbox>
      <xmin>1495.47</xmin>
      <ymin>1235.87</ymin>
      <xmax>1593.68</xmax>
      <ymax>1254.73</ymax>
    </bndbox>
    <attributes>
      <attribute>
        <name>rotation</name>
        <value>0.0</value>
      </attribute>
    </attributes>
  </object>
  <object>
    <name>anntotation_text</name>
    <truncated>0</truncated>
    <occluded>0</occluded>
    <difficult>0</difficult>
    <bndbox>
      <xmin>1222.15</xmin>
      <ymin>1242.8</ymin>
      <xmax>1255.15</xmax>
      <ymax>1276.74</ymax>
    </bndbox>
    <attributes>
      <attribute>
        <name>rotation</name>
        <value>0.0</value>
      </attribute>
    </attributes>
  </object>
  <object>
    <name>anntotation_text</name>
    <truncated>0</truncated>
    <occluded>0</occluded>
    <difficult>0</difficult>
    <bndbox>
      <xmin>938.4</xmin>
      <ymin>1501.67</ymin>
      <xmax>968.26</xmax>
      <ymax>1520.53</ymax>
    </bndbox>
    <attributes>
      <attribute>
        <name>rotation</name>
        <value>0.0</value>
      </attribute>
    </attributes>
  </object>
  <object>
    <name>anntotation_text</name>
    <truncated>0</truncated>
    <occluded>0</occluded>
    <difficult>0</difficult>
    <bndbox>
      <xmin>813.48</xmin>
      <ymin>1434.1</ymin>
      <xmax>853.55</xmax>
      <ymax>1467.89</ymax>
    </bndbox>
    <attributes>
      <attribute>
        <name>rotation</name>
        <value>0.0</value>
      </attribute>
    </attributes>
  </object>
  <object>
    <name>anntotation_text</name>
    <truncated>0</truncated>
    <occluded>0</occluded>
    <difficult>0</difficult>
    <bndbox>
      <xmin>124.81</xmin>
      <ymin>1574.43</ymin>
      <xmax>202.04</xmax>
      <ymax>1586.85</ymax>
    </bndbox>
    <attributes>
      <attribute>
        <name>rotation</name>
        <value>0.0</value>
      </attribute>
    </attributes>
  </object>
  <object>
    <name>anntotation_text</name>
    <truncated>0</truncated>
    <occluded>0</occluded>
    <difficult>0</difficult>
    <bndbox>
      <xmin>146.08</xmin>
      <ymin>1059.81</ymin>
      <xmax>671.06</xmax>
      <ymax>1420.73</ymax>
    </bndbox>
    <attributes>
      <attribute>
        <name>rotation</name>
        <value>0.0</value>
      </attribute>
    </attributes>
  </object>
  <object>
    <name>anntotation_text</name>
    <truncated>0</truncated>
    <occluded>0</occluded>
    <difficult>0</difficult>
    <bndbox>
      <xmin>860.57</xmin>
      <ymin>1037.07</ymin>
      <xmax>1063.09</xmax>
      <ymax>1057.44</ymax>
    </bndbox>
    <attributes>
      <attribute>
        <name>rotation</name>
        <value>0.0</value>
      </attribute>
    </attributes>
  </object>
  <object>
    <name>anntotation_text</name>
    <truncated>0</truncated>
    <occluded>0</occluded>
    <difficult>0</difficult>
    <bndbox>
      <xmin>826.63</xmin>
      <ymin>947.24</ymin>
      <xmax>1042.62</xmax>
      <ymax>994.08</ymax>
    </bndbox>
    <attributes>
      <attribute>
        <name>rotation</name>
        <value>0.0</value>
      </attribute>
    </attributes>
  </object>
  <object>
    <name>anntotation_text</name>
    <truncated>0</truncated>
    <occluded>0</occluded>
    <difficult>0</difficult>
    <bndbox>
      <xmin>446.16</xmin>
      <ymin>925.6</ymin>
      <xmax>558.52</xmax>
      <ymax>947.6</ymax>
    </bndbox>
    <attributes>
      <attribute>
        <name>rotation</name>
        <value>0.0</value>
      </attribute>
    </attributes>
  </object>
  <object>
    <name>anntotation_text</name>
    <truncated>0</truncated>
    <occluded>0</occluded>
    <difficult>0</difficult>
    <bndbox>
      <xmin>475.42</xmin>
      <ymin>779.96</ymin>
      <xmax>493.33</xmax>
      <ymax>801.64</ymax>
    </bndbox>
    <attributes>
      <attribute>
        <name>rotation</name>
        <value>0.0</value>
      </attribute>
    </attributes>
  </object>
  <object>
    <name>anntotation_text</name>
    <truncated>0</truncated>
    <occluded>0</occluded>
    <difficult>0</difficult>
    <bndbox>
      <xmin>233.09</xmin>
      <ymin>632.66</ymin>
      <xmax>262.96</xmax>
      <ymax>661.17</ymax>
    </bndbox>
    <attributes>
      <attribute>
        <name>rotation</name>
        <value>0.0</value>
      </attribute>
    </attributes>
  </object>
  <object>
    <name>anntotation_text</name>
    <truncated>0</truncated>
    <occluded>0</occluded>
    <difficult>0</difficult>
    <bndbox>
      <xmin>201.86</xmin>
      <ymin>386.92</ymin>
      <xmax>305.05</xmax>
      <ymax>412.71</ymax>
    </bndbox>
    <attributes>
      <attribute>
        <name>rotation</name>
        <value>0.0</value>
      </attribute>
    </attributes>
  </object>
  <object>
    <name>anntotation_text</name>
    <truncated>0</truncated>
    <occluded>0</occluded>
    <difficult>0</difficult>
    <bndbox>
      <xmin>205.94</xmin>
      <ymin>145.25</ymin>
      <xmax>307.76</xmax>
      <ymax>171.04</ymax>
    </bndbox>
    <attributes>
      <attribute>
        <name>rotation</name>
        <value>0.0</value>
      </attribute>
    </attributes>
  </object>
  <object>
    <name>anntotation_text</name>
    <truncated>0</truncated>
    <occluded>0</occluded>
    <difficult>0</difficult>
    <bndbox>
      <xmin>634.97</xmin>
      <ymin>158.82</ymin>
      <xmax>663.48</xmax>
      <ymax>185.98</ymax>
    </bndbox>
    <attributes>
      <attribute>
        <name>rotation</name>
        <value>0.0</value>
      </attribute>
    </attributes>
  </object>
  <object>
    <name>anntotation_text</name>
    <truncated>0</truncated>
    <occluded>0</occluded>
    <difficult>0</difficult>
    <bndbox>
      <xmin>754.45</xmin>
      <ymin>632.66</ymin>
      <xmax>782.96</xmax>
      <ymax>659.81</ymax>
    </bndbox>
    <attributes>
      <attribute>
        <name>rotation</name>
        <value>0.0</value>
      </attribute>
    </attributes>
  </object>
  <object>
    <name>anntotation_text</name>
    <truncated>0</truncated>
    <occluded>0</occluded>
    <difficult>0</difficult>
    <bndbox>
      <xmin>1418.4</xmin>
      <ymin>274.2</ymin>
      <xmax>1522.9</xmax>
      <ymax>293.24</ymax>
    </bndbox>
    <attributes>
      <attribute>
        <name>rotation</name>
        <value>0.0</value>
      </attribute>
    </attributes>
  </object>
  <object>
    <name>anntotation_text</name>
    <truncated>0</truncated>
    <occluded>0</occluded>
    <difficult>0</difficult>
    <bndbox>
      <xmin>1281.23</xmin>
      <ymin>302.74</ymin>
      <xmax>1433.29</xmax>
      <ymax>355.69</ymax>
    </bndbox>
    <attributes>
      <attribute>
        <name>rotation</name>
        <value>0.0</value>
      </attribute>
    </attributes>
  </object>
  <object>
    <name>object</name>
    <truncated>0</truncated>
    <occluded>0</occluded>
    <difficult>0</difficult>
    <bndbox>
      <xmin>1332.82</xmin>
      <ymin>203.63</ymin>
      <xmax>1402.07</xmax>
      <ymax>248.43</ymax>
    </bndbox>
    <attributes>
      <attribute>
        <name>rotation</name>
        <value>0.0</value>
      </attribute>
    </attributes>
  </object>
  <object>
    <name>anntotation_text</name>
    <truncated>0</truncated>
    <occluded>0</occluded>
    <difficult>0</difficult>
    <bndbox>
      <xmin>1388.94</xmin>
      <ymin>430.63</ymin>
      <xmax>1569.97</xmax>
      <ymax>467.97</ymax>
    </bndbox>
    <attributes>
      <attribute>
        <name>rotation</name>
        <value>0.0</value>
      </attribute>
    </attributes>
  </object>
  <object>
    <name>anntotation_text</name>
    <truncated>0</truncated>
    <occluded>0</occluded>
    <difficult>0</difficult>
    <bndbox>
      <xmin>1686.64</xmin>
      <ymin>330.63</ymin>
      <xmax>2238.13</xmax>
      <ymax>375.76</ymax>
    </bndbox>
    <attributes>
      <attribute>
        <name>rotation</name>
        <value>0.0</value>
      </attribute>
    </attributes>
  </object>
  <object>
    <name>dimension_text</name>
    <truncated>0</truncated>
    <occluded>0</occluded>
    <difficult>0</difficult>
    <bndbox>
      <xmin>368.22</xmin>
      <ymin>589.79</ymin>
      <xmax>383.3</xmax>
      <ymax>677.47</ymax>
    </bndbox>
    <attributes>
      <attribute>
        <name>rotation</name>
        <value>24.10000000000001</value>
      </attribute>
    </attributes>
  </object>
  <object>
    <name>dimension_text</name>
    <truncated>0</truncated>
    <occluded>0</occluded>
    <difficult>0</difficult>
    <bndbox>
      <xmin>547.08</xmin>
      <ymin>733.38</ymin>
      <xmax>562.16</xmax>
      <ymax>754.97</ymax>
    </bndbox>
    <attributes>
      <attribute>
        <name>rotation</name>
        <value>0.0</value>
      </attribute>
    </attributes>
  </object>
  <object>
    <name>dimension_text</name>
    <truncated>0</truncated>
    <occluded>0</occluded>
    <difficult>0</difficult>
    <bndbox>
      <xmin>579.13</xmin>
      <ymin>726.69</ymin>
      <xmax>594.22</xmax>
      <ymax>758.74</ymax>
    </bndbox>
    <attributes>
      <attribute>
        <name>rotation</name>
        <value>0.0</value>
      </attribute>
    </attributes>
  </object>
  <object>
    <name>dimension_text</name>
    <truncated>0</truncated>
    <occluded>0</occluded>
    <difficult>0</difficult>
    <bndbox>
      <xmin>609.3</xmin>
      <ymin>726.69</ymin>
      <xmax>625.33</xmax>
      <ymax>760.63</ymax>
    </bndbox>
    <attributes>
      <attribute>
        <name>rotation</name>
        <value>0.0</value>
      </attribute>
    </attributes>
  </object>
  <object>
    <name>dimension_text</name>
    <truncated>0</truncated>
    <occluded>0</occluded>
    <difficult>0</difficult>
    <bndbox>
      <xmin>641.94</xmin>
      <ymin>624.48</ymin>
      <xmax>657.97</xmax>
      <ymax>643.43</ymax>
    </bndbox>
    <attributes>
      <attribute>
        <name>rotation</name>
        <value>310.8</value>
      </attribute>
    </attributes>
  </object>
  <object>
    <name>dimension_text</name>
    <truncated>0</truncated>
    <occluded>0</occluded>
    <difficult>0</difficult>
    <bndbox>
      <xmin>710.33</xmin>
      <ymin>625.05</ymin>
      <xmax>726.36</xmax>
      <ymax>644.0</ymax>
    </bndbox>
    <attributes>
      <attribute>
        <name>rotation</name>
        <value>308.2</value>
      </attribute>
    </attributes>
  </object>
  <object>
    <name>dimension_text</name>
    <truncated>0</truncated>
    <occluded>0</occluded>
    <difficult>0</difficult>
    <bndbox>
      <xmin>687.28</xmin>
      <ymin>506.53</ymin>
      <xmax>703.3</xmax>
      <ymax>522.56</ymax>
    </bndbox>
    <attributes>
      <attribute>
        <name>rotation</name>
        <value>0.0</value>
      </attribute>
    </attributes>
  </object>
  <object>
    <name>dimension_text</name>
    <truncated>0</truncated>
    <occluded>0</occluded>
    <difficult>0</difficult>
    <bndbox>
      <xmin>857.93</xmin>
      <ymin>475.42</ymin>
      <xmax>979.56</xmax>
      <ymax>493.33</ymax>
    </bndbox>
    <attributes>
      <attribute>
        <name>rotation</name>
        <value>0.0</value>
      </attribute>
    </attributes>
  </object>
  <object>
    <name>dimension_text</name>
    <truncated>0</truncated>
    <occluded>0</occluded>
    <difficult>0</difficult>
    <bndbox>
      <xmin>866.42</xmin>
      <ymin>506.53</ymin>
      <xmax>988.04</xmax>
      <ymax>524.45</ymax>
    </bndbox>
    <attributes>
      <attribute>
        <name>rotation</name>
        <value>0.0</value>
      </attribute>
    </attributes>
  </object>
  <object>
    <name>dimension_text</name>
    <truncated>0</truncated>
    <occluded>0</occluded>
    <difficult>0</difficult>
    <bndbox>
      <xmin>1012.99</xmin>
      <ymin>541.03</ymin>
      <xmax>1022.54</xmax>
      <ymax>556.03</ymax>
    </bndbox>
    <attributes>
      <attribute>
        <name>rotation</name>
        <value>0.0</value>
      </attribute>
    </attributes>
  </object>
  <object>
    <name>dimension_text</name>
    <truncated>0</truncated>
    <occluded>0</occluded>
    <difficult>0</difficult>
    <bndbox>
      <xmin>1082.61</xmin>
      <ymin>540.43</ymin>
      <xmax>1112.62</xmax>
      <ymax>555.44</ymax>
    </bndbox>
    <attributes>
      <attribute>
        <name>rotation</name>
        <value>0.0</value>
      </attribute>
    </attributes>
  </object>
  <object>
    <name>dimension_text</name>
    <truncated>0</truncated>
    <occluded>0</occluded>
    <difficult>0</difficult>
    <bndbox>
      <xmin>1168.54</xmin>
      <ymin>569.99</ymin>
      <xmax>1193.1</xmax>
      <ymax>586.81</ymax>
    </bndbox>
    <attributes>
      <attribute>
        <name>rotation</name>
        <value>0.0</value>
      </attribute>
    </attributes>
  </object>
  <object>
    <name>dimension_text</name>
    <truncated>0</truncated>
    <occluded>0</occluded>
    <difficult>0</difficult>
    <bndbox>
      <xmin>1175.36</xmin>
      <ymin>601.82</ymin>
      <xmax>1192.64</xmax>
      <ymax>618.19</ymax>
    </bndbox>
    <attributes>
      <attribute>
        <name>rotation</name>
        <value>0.0</value>
      </attribute>
    </attributes>
  </object>
  <object>
    <name>dimension_text</name>
    <truncated>0</truncated>
    <occluded>0</occluded>
    <difficult>0</difficult>
    <bndbox>
      <xmin>1193.29</xmin>
      <ymin>936.05</ymin>
      <xmax>1209.0</xmax>
      <ymax>1019.33</ymax>
    </bndbox>
    <attributes>
      <attribute>
        <name>rotation</name>
        <value>0.0</value>
      </attribute>
    </attributes>
  </object>
  <object>
    <name>dimension_text</name>
    <truncated>0</truncated>
    <occluded>0</occluded>
    <difficult>0</difficult>
    <bndbox>
      <xmin>1223.93</xmin>
      <ymin>910.9</ymin>
      <xmax>1241.21</xmax>
      <ymax>1013.83</ymax>
    </bndbox>
    <attributes>
      <attribute>
        <name>rotation</name>
        <value>0.0</value>
      </attribute>
    </attributes>
  </object>
  <object>
    <name>anntotation_text</name>
    <truncated>0</truncated>
    <occluded>0</occluded>
    <difficult>0</difficult>
    <bndbox>
      <xmin>1128.07</xmin>
      <ymin>1184.33</ymin>
      <xmax>1146.14</xmax>
      <ymax>1200.83</ymax>
    </bndbox>
    <attributes>
      <attribute>
        <name>rotation</name>
        <value>0.0</value>
      </attribute>
    </attributes>
  </object>
  <object>
    <name>anntotation_text</name>
    <truncated>0</truncated>
    <occluded>0</occluded>
    <difficult>0</difficult>
    <bndbox>
      <xmin>1278.93</xmin>
      <ymin>782.05</ymin>
      <xmax>1297.0</xmax>
      <ymax>803.26</ymax>
    </bndbox>
    <attributes>
      <attribute>
        <name>rotation</name>
        <value>0.0</value>
      </attribute>
    </attributes>
  </object>
  <object>
    <name>anntotation_text</name>
    <truncated>0</truncated>
    <occluded>0</occluded>
    <difficult>0</difficult>
    <bndbox>
      <xmin>1528.78</xmin>
      <ymin>632.76</ymin>
      <xmax>1544.5</xmax>
      <ymax>648.48</ymax>
    </bndbox>
    <attributes>
      <attribute>
        <name>rotation</name>
        <value>0.0</value>
      </attribute>
    </attributes>
  </object>
  <object>
    <name>dimension_text</name>
    <truncated>0</truncated>
    <occluded>0</occluded>
    <difficult>0</difficult>
    <bndbox>
      <xmin>1536.64</xmin>
      <ymin>795.41</ymin>
      <xmax>1622.28</xmax>
      <ymax>815.05</ymax>
    </bndbox>
    <attributes>
      <attribute>
        <name>rotation</name>
        <value>31.099999999999994</value>
      </attribute>
    </attributes>
  </object>
  <object>
    <name>dimension_text</name>
    <truncated>0</truncated>
    <occluded>0</occluded>
    <difficult>0</difficult>
    <bndbox>
      <xmin>1708.32</xmin>
      <ymin>905.19</ymin>
      <xmax>1745.58</xmax>
      <ymax>919.98</ymax>
    </bndbox>
    <attributes>
      <attribute>
        <name>rotation</name>
        <value>314.29999999999995</value>
      </attribute>
    </attributes>
  </object>
  <object>
    <name>dimension_text</name>
    <truncated>0</truncated>
    <occluded>0</occluded>
    <difficult>0</difficult>
    <bndbox>
      <xmin>1915.01</xmin>
      <ymin>986.57</ymin>
      <xmax>1932.68</xmax>
      <ymax>1035.67</ymax>
    </bndbox>
    <attributes>
      <attribute>
        <name>rotation</name>
        <value>14.299999999999997</value>
      </attribute>
    </attributes>
  </object>
  <object>
    <name>dimension_text</name>
    <truncated>0</truncated>
    <occluded>0</occluded>
    <difficult>0</difficult>
    <bndbox>
      <xmin>2178.72</xmin>
      <ymin>711.89</ymin>
      <xmax>2192.07</xmax>
      <ymax>759.81</ymax>
    </bndbox>
    <attributes>
      <attribute>
        <name>rotation</name>
        <value>0.0</value>
      </attribute>
    </attributes>
  </object>
  <object>
    <name>dimension_text</name>
    <truncated>0</truncated>
    <occluded>0</occluded>
    <difficult>0</difficult>
    <bndbox>
      <xmin>2213.29</xmin>
      <ymin>606.6</ymin>
      <xmax>2229.79</xmax>
      <ymax>700.1</ymax>
    </bndbox>
    <attributes>
      <attribute>
        <name>rotation</name>
        <value>0.0</value>
      </attribute>
    </attributes>
  </object>
  <object>
    <name>title_block</name>
    <truncated>0</truncated>
    <occluded>0</occluded>
    <difficult>0</difficult>
    <bndbox>
      <xmin>1553.7</xmin>
      <ymin>121.25</ymin>
      <xmax>2250.28</xmax>
      <ymax>313.0</ymax>
    </bndbox>
    <attributes>
      <attribute>
        <name>rotation</name>
        <value>0.0</value>
      </attribute>
      <attribute>
        <name>track_id</name>
        <value>5</value>
      </attribute>
      <attribute>
        <name>keyframe</name>
        <value>True</value>
      </attribute>
    </attributes>
  </object>
</annotation>
